my_download/my_download.py
my_download-0.2.0.dist-info/METADATA
my_download-0.2.0.dist-info/WHEEL
my_download-0.2.0.dist-info/license.txt
my_download-0.2.0.dist-info/top_level.txt
my_download-0.2.0.dist-info/zip-safe
my_download-0.2.0.dist-info/RECORD
